setup.py
lyhtools/__init__.py
lyhtools.egg-info/PKG-INFO
lyhtools.egg-info/SOURCES.txt
lyhtools.egg-info/dependency_links.txt
lyhtools.egg-info/top_level.txt
lyhtools/finance/__init__.py
lyhtools/finance/binomtree.py
lyhtools/finance/capm.py
lyhtools/finance/options.py
lyhtools/linear/__init__.py
lyhtools/linear/regression.py
lyhtools/linear/samples.py
lyhtools/vis/__init__.py
lyhtools/vis/table.py