Metadata-Version: 1.0
Name: lyhtools
Version: 0.1.0
Summary: a library for some statistics implementation
Home-page: UNKNOWN
Author: Yiheng Li
Author-email: liyiheng.scott@gmail.com
License: MIT License
Keywords: yiheng statistics
Platform: any
